ramalama_stack/__init__.py
ramalama_stack/_version.py
ramalama_stack/config.py
ramalama_stack/models.py
ramalama_stack/openai_compat.py
ramalama_stack/provider.py
ramalama_stack/ramalama-run.yaml
ramalama_stack/ramalama_adapter.py
ramalama_stack/providers.d/remote/inference/ramalama.yaml
ramalama_stack-0.2.5.dist-info/licenses/LICENSE
ramalama_stack-0.2.5.dist-info/METADATA
ramalama_stack-0.2.5.dist-info/WHEEL
ramalama_stack-0.2.5.dist-info/top_level.txt
ramalama_stack-0.2.5.dist-info/RECORD
