Metadata-Version: 2.4
Name: ramalama-stack
Version: 0.2.5
Summary: An external provider for Llama Stack allowing for the use of RamaLama for inference.
Author: The RamaLama Stack Authors
License-Expression: Apache-2.0
Project-URL: homepage, https://ramalama.ai
Project-URL: Repository, https://github.com/containers/ramalama-stack
Project-URL: Issues, https://github.com/containers/ramalama-stack/issues
Keywords: ramalama,llama,AI
Requires-Python: >=3.12
License-File: LICENSE
Requires-Dist: aiohttp>=3.12.2
Requires-Dist: aiosqlite>=0.21.0
Requires-Dist: autoevals>=0.0.129
Requires-Dist: blobfile>=3.0.0
Requires-Dist: chardet>=3.0.0
Requires-Dist: datasets>=3.6.0
Requires-Dist: fastapi>=0.115.12
Requires-Dist: httpx>=0.28.1
Requires-Dist: llama-stack==0.2.14
Requires-Dist: mcp>=1.9.2
Requires-Dist: numpy>=2.2.6
Requires-Dist: openai>=1.82.0
Requires-Dist: opentelemetry-exporter-otlp-proto-http>=1.33.1
Requires-Dist: opentelemetry-sdk>=1.33.1
Requires-Dist: peft>=0.15.2
Requires-Dist: psutil>=7.0.0
Requires-Dist: pydantic>=2.11.5
Requires-Dist: pymilvus>=2.5.10
Requires-Dist: ramalama==0.10.1
Requires-Dist: requests>=2.32.3
Requires-Dist: sentence-transformers>=3.0.0
Requires-Dist: six>=1.17.0
Requires-Dist: sqlalchemy>=2.0.41
Requires-Dist: torch>=2.7.0
Requires-Dist: trl>=0.18.1
Requires-Dist: urllib3>=2.4.0
Requires-Dist: uvicorn>=0.34.2
Dynamic: license-file
